tutorial_package_sid/__init__.py
tutorial_package_sid/greet.py
tutorial_package_sid-0.0.1.dist-info/metadata.json
tutorial_package_sid-0.0.1.dist-info/WHEEL
tutorial_package_sid-0.0.1.dist-info/top_level.txt
tutorial_package_sid-0.0.1.dist-info/METADATA
tutorial_package_sid-0.0.1.dist-info/RECORD
tutorial_package_sid-0.0.1.dist-info/DESCRIPTION.rst
