Metadata-Version: 2.0
Name: tutorial-package-sid
Version: 0.0.1
Summary: A demonstration of how to create and publish python packages
Home-page: UNKNOWN
Author: Siddharth Singh
Author-email: UNKNOWN
License: BSD
Platform: UNKNOWN
